gifparse
