Metadata-Version: 1.1
Name: gifparse
Version: 0.0.1
Summary: [Work in progress.] Parse the GIF 89a file format, down to the minor details. Pure Python, no dependencies.
Home-page: http://github.com/jsvine/gifparse/
Author: Jeremy Singer-Vine
Author-email: jsvine@gmail.com
License: MIT
Keywords: gif gifs 89a
Platform: UNKNOWN
Classifier: Development Status :: 3 - Alpha
Classifier: Intended Audience :: Developers
Classifier: License :: OSI Approved :: MIT License
Classifier: Operating System :: OS Independent
Classifier: Programming Language :: Python :: 2.6
Classifier: Programming Language :: Python :: 2.7
Classifier: Programming Language :: Python :: 3.3
